odoo/addons/ssi_transaction_open_mixin/README.rst
odoo/addons/ssi_transaction_open_mixin/__init__.py
odoo/addons/ssi_transaction_open_mixin/__manifest__.py
odoo/addons/ssi_transaction_open_mixin/i18n/ssi_transaction_open_mixin.pot
odoo/addons/ssi_transaction_open_mixin/models/__init__.py
odoo/addons/ssi_transaction_open_mixin/models/mixin_transaction_open.py
odoo/addons/ssi_transaction_open_mixin/static/description/icon.png
odoo/addons/ssi_transaction_open_mixin/templates/mixin_transaction_open_templates.xml
odoo14_addon_ssi_transaction_open_mixin-14.0.1.13.1.dist-info/METADATA
odoo14_addon_ssi_transaction_open_mixin-14.0.1.13.1.dist-info/WHEEL
odoo14_addon_ssi_transaction_open_mixin-14.0.1.13.1.dist-info/top_level.txt
odoo14_addon_ssi_transaction_open_mixin-14.0.1.13.1.dist-info/RECORD
